[
  {"version":1},
  {"ingredient":{"id":"sophisticatedstorage:chest","components":{"sophisticatedstorage:wood_type":"jungle","sophisticatedstorage:double_chest":true}},"type":"item_stack","bookmarkType":"INGREDIENT"},
  {"ingredient":{"id":"sophisticatedstorage:copper_chest","components":{"sophisticatedstorage:wood_type":"jungle","sophisticatedstorage:double_chest":true}},"type":"item_stack","bookmarkType":"INGREDIENT"},
  {"ingredient":{"id":"minecraft:copper_ingot"},"type":"item_stack","bookmarkType":"INGREDIENT"},
  {"ingredient":{"id":"minecraft:iron_shovel"},"type":"item_stack","bookmarkType":"INGREDIENT"},
  {"ingredient":{"id":"minecraft:furnace"},"type":"item_stack","bookmarkType":"INGREDIENT"},
  {"ingredient":{"id":"sophisticatedbackpacks:backpack"},"type":"item_stack","bookmarkType":"INGREDIENT"},
  {"ingredient":{"id":"minecraft:chest"},"type":"item_stack","bookmarkType":"INGREDIENT"},
  {"ingredient":{"id":"minecraft:raw_copper"},"type":"item_stack","bookmarkType":"INGREDIENT"},
  {"ingredient":{"id":"minecraft:smithing_table"},"type":"item_stack","bookmarkType":"INGREDIENT"},
  {"ingredient":{"id":"vc_gliders:paraglider_iron","components":{"vc_gliders:struck":false,"vc_gliders:glide":false,"minecraft:damage":18}},"type":"item_stack","bookmarkType":"INGREDIENT"}
]